Verilog/cla_adder.v
module cla_adder (
    input wire clk,
    input wire [4:0] a,
    input wire [4:0] b,
    output reg [4:0] sum,
    output reg cout
);

    reg [4:0] a_reg, b_reg;
    
    wire [4:0] p, g; 
    wire [5:0] c; 
    wire [4:0] sum_wire;
    
    always @(posedge clk) begin
        a_reg <= a;
        b_reg <= b;
    end
    
    assign p = a_reg ^ b_reg; 
    assign g = a_reg & b_reg; 
    
    assign c[0] = 1'b0; 
    assign c[1] = g[0] | (p[0] & c[0]);
    assign c[2] = g[1] | (p[1] & g[0]) | (p[1] & p[0] & c[0]);
    assign c[3] = g[2] | (p[2] & g[1]) | (p[2] & p[1] & g[0]) | (p[2] & p[1] & p[0] & c[0]);
    assign c[4] = g[3] | (p[3] & g[2]) | (p[3] & p[2] & g[1]) | (p[3] & p[2] & p[1] & g[0]) | (p[3] & p[2] & p[1] & p[0] & c[0]);
    
    assign c[5] = g[4] | 
                  (p[4] & g[3]) | 
                  (p[4] & p[3] & g[2]) | 
                  (p[4] & p[3] & p[2] & g[1]) | 
                  (p[4] & p[3] & p[2] & p[1] & g[0]) | 
                  (p[4] & p[3] & p[2] & p[1] & p[0] & c[0]);
    
    assign sum_wire = p ^ c[4:0]; 
    
    always @(posedge clk) begin
        sum <= sum_wire;
        cout <= c[5];
    end
    
endmodule

Verilog/cla_adder_tb.v
`timescale 1ns / 1ps

module cla_adder_tb;
    // Inputs
    reg clk;
    reg [4:0] a;
    reg [4:0] b;
    // Outputs
    wire [4:0] sum;
    wire cout;
    // Instantiate the DUT
    cla_adder uut (
        .clk(clk),
        .a(a),
        .b(b),
        .sum(sum),
        .cout(cout)
    );
    // Clock generation
    initial clk = 0;
    always #5 clk = ~clk;
    // Stimulus
    initial begin
        a = 0; b = 0;
        #10;  a = 5'b00000;  b = 5'b00000;
        #10;  a = 5'b00101;  b = 5'b00011;
        #10;  a = 5'b01111;  b = 5'b00001;
        #10;  a = 5'b11111;  b = 5'b00001;
        #10;  a = 5'b10101;  b = 5'b01011;
        #20;
        $finish;
    end
    // Waveform + Monitor
    initial begin
        $dumpfile("cla_adder.vcd");
        $dumpvars(0, cla_adder_tb);
        $monitor("Time=%0t a=%05b b=%05b sum=%05b cout=%b",
                  $time, a, b, sum, cout);
    end

endmodule

Verilog/cla_adder.vcd
$date
	Tue Dec 02 12:55:13 2025
$end
$version
	Icarus Verilog
$end
$timescale
	1ps
$end
$scope module cla_adder_tb $end
$var wire 5 ! sum [4:0] $end
$var wire 1 " cout $end
$var reg 5 # a [4:0] $end
$var reg 5 $ b [4:0] $end
$var reg 1 % clk $end
$scope module uut $end
$var wire 5 & a [4:0] $end
$var wire 5 ' b [4:0] $end
$var wire 1 % clk $end
$var wire 5 ( g [4:0] $end
$var wire 5 ) p [4:0] $end
$var wire 5 * sum_wire [4:0] $end
$var wire 6 + c [5:0] $end
$var reg 5 , a_reg [4:0] $end
$var reg 5 - b_reg [4:0] $end
$var reg 1 " cout $end
$var reg 5 . sum [4:0] $end
$upscope $end
$upscope $end
$enddefinitions $end
$comment Show the parameter values. $end
$dumpall
$end
#0
$dumpvars
bx .
bx -
bx ,
bx0 +
bx *
bx )
bx (
b0 '
b0 &
0%
b0 $
b0 #
x"
bx !
$end
#5000
b0 +
b0 *
b0 (
b0 )
b0 -
b0 ,
1%
#10000
0%
#15000
0"
b0 !
b0 .
1%
#20000
0%
b11 $
b11 '
b101 #
b101 &
#25000
b1110 +
b1000 *
b1 (
b110 )
b11 -
b101 ,
1%
#30000
0%
b1 $
b1 '
b1111 #
b1111 &
#35000
b11110 +
b10000 *
b1110 )
b1000 !
b1000 .
b1 -
b1111 ,
1%
#40000
0%
b11111 #
b11111 &
#45000
b111110 +
b0 *
b11110 )
b11111 ,
b10000 !
b10000 .
1%
#50000
0%
b1011 $
b1011 '
b10101 #
b10101 &
#55000
1"
b0 !
b0 .
b1011 -
b10101 ,
1%
